ml4ht/__init__.py
ml4ht/data/__init__.py
ml4ht/data/data_description.py
ml4ht/data/data_loader.py
ml4ht/data/defines.py
ml4ht/data/explore.py
ml4ht/data/sample_getter.py
ml4ht/data/util/__init__.py
ml4ht/data/util/data_frame_data_description.py
ml4ht/data/util/date_selector.py
ml4ht-0.0.4.dist-info/METADATA
ml4ht-0.0.4.dist-info/WHEEL
ml4ht-0.0.4.dist-info/top_level.txt
ml4ht-0.0.4.dist-info/RECORD
